fetpapi.libs/libFesapiCpp-e3328c3a.so.2.12.1.0
fetpapi.libs/libminizip-7f4289bd.so.1.0.0
fetpapi.libs/libFetpapi-4e5a77c1.so.0.3.1.0
fetpapi.libs/libsz-0deeef7d.so.2.0.1
fetpapi.libs/libhdf5-b5e70f84.so.103.1.0
fetpapi.libs/libcrypto-bdaed0ea.so.1.1.1k
fetpapi.libs/libboost_system-69a6c43e.so.1.66.0
fetpapi.libs/libssl-60250281.so.1.1.1k
fetpapi.libs/libaec-91f0ca0f.so.0.0.8
fetpapi/_fetpapi.cpython-313-x86_64-linux-gnu.so
fetpapi/__init__.py
fetpapi-0.3.1.dist-info/METADATA
fetpapi-0.3.1.dist-info/RECORD
fetpapi-0.3.1.dist-info/top_level.txt
fetpapi-0.3.1.dist-info/WHEEL
