Metadata-Version: 2.2
Name: fetpapi
Version: 0.3.1
Summary: A library for using the Energistics Transfer Protocol
Author: F2I-CONSULTING
Maintainer: F2I-CONSULTING
Project-URL: source, https://github.com/F2I-Consulting/fetpapi/issues
Project-URL: releasenotes, https://github.com/F2I-Consulting/fetpapi/releases
Project-URL: documentation, https://www.f2i-consulting.com/fetpapi/doxygen/
Project-URL: issues, https://github.com/F2I-Consulting/fetpapi/issues
Keywords: energistics,resqml,eml,witsml,prodml,osdu,rddms
Classifier: Development Status :: 5 - Production/Stable
Classifier: Intended Audience :: Developers
Classifier: License :: OSI Approved :: Apache Software License
Classifier: Operating System :: Microsoft :: Windows
Classifier: Operating System :: POSIX :: Linux
Classifier: Operating System :: MacOS
Classifier: Natural Language :: English
Classifier: Programming Language :: Python :: 3
Classifier: Programming Language :: Python :: 3.8
Classifier: Programming Language :: Python :: 3.9
Classifier: Programming Language :: Python :: 3.10
Classifier: Programming Language :: Python :: 3.11
Classifier: Programming Language :: Python :: 3.12
Classifier: Topic :: Software Development
Classifier: Topic :: Software Development :: Libraries
Classifier: Topic :: Software Development :: Libraries :: Application Frameworks 
Classifier: Topic :: File Formats
Requires-Python: >=3.8
Requires-Dist: fesapi==2.12.1
